spam_detector_ai/__init__.py
spam_detector_ai/logger_config.py
spam_detector_ai/trainer.py
spam_detector_ai/classifiers/__init__.py
spam_detector_ai/classifiers/base_classifier.py
spam_detector_ai/classifiers/classifier_types.py
spam_detector_ai/classifiers/logistic_regression_classifier.py
spam_detector_ai/classifiers/naive_bayes_classifier.py
spam_detector_ai/classifiers/random_forest_classifier.py
spam_detector_ai/classifiers/svm_classifier.py
spam_detector_ai/classifiers/xgb_classifier.py
spam_detector_ai/loading_and_processing/__init__.py
spam_detector_ai/loading_and_processing/data_loader.py
spam_detector_ai/loading_and_processing/preprocessor.py
spam_detector_ai/models/bayes/naive_bayes_model.joblib
spam_detector_ai/models/bayes/naive_bayes_vectoriser.joblib
spam_detector_ai/models/logistic_regression/logistic_regression_model.joblib
spam_detector_ai/models/logistic_regression/logistic_regression_vectoriser.joblib
spam_detector_ai/models/random_forest/random_forest_model.joblib
spam_detector_ai/models/random_forest/random_forest_vectoriser.joblib
spam_detector_ai/models/svm/svm_model.joblib
spam_detector_ai/models/svm/svm_vectoriser.joblib
spam_detector_ai/models/xgb/xgb_model.joblib
spam_detector_ai/models/xgb/xgb_model.json
spam_detector_ai/models/xgb/xgb_vectoriser.joblib
spam_detector_ai/models/xgb/xgb_vectoriser_label_encoder.joblib
spam_detector_ai/prediction/__init__.py
spam_detector_ai/prediction/performance.py
spam_detector_ai/prediction/predict.py
spam_detector_ai/tests/__init__.py
spam_detector_ai/tests/launcher.py
spam_detector_ai/tests/py_test.py
spam_detector_ai/tests/test.py
spam_detector_ai/tests/test_dataloader.py
spam_detector_ai/tests/test_preprocessor.py
spam_detector_ai/training/__init__.py
spam_detector_ai/training/train_models.py
spam_detector_ai/tuning/__init__.py
spam_detector_ai/tuning/fine_tuning_logistic_regression.py
spam_detector_ai/tuning/fine_tuning_svm.py
spam_detector_ai/tuning/fine_tuning_xgb.py
spam_detector_ai-2.1.19.dist-info/licenses/LICENSE
spam_detector_ai-2.1.19.dist-info/METADATA
spam_detector_ai-2.1.19.dist-info/WHEEL
spam_detector_ai-2.1.19.dist-info/top_level.txt
spam_detector_ai-2.1.19.dist-info/RECORD
