Metadata-Version: 2.4
Name: spam-detector-ai
Version: 2.1.19
Summary: A package for detecting and filtering spam messages using Machine Learning models.
Home-page: https://github.com/adamspd/spam-detection-project
Author: Adams Pierre David
Author-email: spam-detection-api@adamspierredavid.com
License: MIT
Project-URL: API Documentation, https://spam-detection-api.adamspierredavid.com/redoc/
Project-URL: Author's Website, https://adamspierredavid.com/
Project-URL: Bug Tracker, https://github.com/adamspd/spam-detection-project/issues
Project-URL: Contact Page, https://adamspierredavid.com/contact/
Classifier: Environment :: Console
Classifier: Intended Audience :: Developers
Classifier: Operating System :: OS Independent
Classifier: Programming Language :: Python
Classifier: Programming Language :: Python :: 3
Classifier: Programming Language :: Python :: 3.8
Classifier: Programming Language :: Python :: 3.9
Classifier: Programming Language :: Python :: 3.10
Classifier: Programming Language :: Python :: 3.11
Classifier: Programming Language :: Python :: 3.12
Classifier: Topic :: Text Processing
Classifier: Topic :: Scientific/Engineering :: Artificial Intelligence
Requires-Python: >=3.8
License-File: LICENSE
Requires-Dist: scikit-learn<2.0.0,>=1.7.0
Requires-Dist: imbalanced-learn<0.15.0,>=0.14.0
Requires-Dist: pandas<3.0.0,>=2.3.0
Requires-Dist: nltk<4.0.0,>=3.9.0
Requires-Dist: joblib<2.0.0,>=1.5.0
Requires-Dist: xgboost<4.0.0,>=3.1.0
Requires-Dist: numpy<3.0.0,>=1.26.0
Dynamic: author
Dynamic: author-email
Dynamic: description
Dynamic: description-content-type
Dynamic: home-page
Dynamic: license-file
Dynamic: project-url
Dynamic: summary
